nonebot_plugin_disconnect_notice/__init__.py
nonebot_plugin_disconnect_notice/config.py
nonebot_plugin_disconnect_notice/dataClass.py
nonebot_plugin_disconnect_notice/notice.py
nonebot_plugin_disconnect_notice/utils.py
nonebot_plugin_disconnect_notice-0.4.2.dist-info/METADATA
nonebot_plugin_disconnect_notice-0.4.2.dist-info/WHEEL
nonebot_plugin_disconnect_notice-0.4.2.dist-info/licenses/LICENSE
nonebot_plugin_disconnect_notice-0.4.2.dist-info/RECORD
