Metadata-Version: 2.4
Name: nonebot-plugin-disconnect-notice
Version: 0.4.2
Summary: bot断连时的通知插件
License-File: LICENSE
Author: cypas
Author-email: ayano05@outlook.com
Requires-Python: >=3.8,<4.0
Classifier: Programming Language :: Python :: 3
Classifier: Programming Language :: Python :: 3.8
Classifier: Programming Language :: Python :: 3.9
Classifier: Programming Language :: Python :: 3.10
Classifier: Programming Language :: Python :: 3.11
Classifier: Programming Language :: Python :: 3.12
Classifier: Programming Language :: Python :: 3.13
Classifier: Programming Language :: Python :: 3.14
Requires-Dist: aiosmtplib (>=2.0.2,<3.0.0)
Requires-Dist: httpx (>=0.28.1,<0.29.0)
Requires-Dist: nonebot-adapter-onebot (>=2.4.1,<3.0.0)
Requires-Dist: nonebot-plugin-apscheduler (>=0.5.0,<0.6.0)
Requires-Dist: nonebot2 (>=2.2.0,<3.0.0)
